[
  {
    "path": "/tianheg/50projects50days",
    "title": "tianheg/50projects50days: Exercise as much as more",
    "count": 37,
    "uniques": 1
  },
  {
    "path": "/tianheg/50projects50days/commits/main",
    "title": "Commits · tianheg/50projects50days",
    "count": 9,
    "uniques": 1
  },
  {
    "path": "/tianheg/50projects50days/issues",
    "title": "Issues · tianheg/50projects50days",
    "count": 3,
    "uniques": 1
  },
  {
    "path": "/tianheg/50projects50days/issues/1",
    "title": "目标网页没有自动添加 `/` 导致浏览器找不到页面 · Issue #1 · tianheg/50projects50days",
    "count": 3,
    "uniques": 1
  },
  {
    "path": "/tianheg/50projects50days/issues/2",
    "title": "目标网页没有自动添加 `index.html` 导致浏览器找不到页面 · Issue #2 · tianheg/50projects50days",
    "count": 2,
    "uniques": 1
  },
  {
    "path": "/tianheg/50projects50days/issues/new",
    "title": "New Issue · tianheg/50projects50days",
    "count": 2,
    "uniques": 1
  },
  {
    "path": "/tianheg/50projects50days/blob/main/animated-navigation/index.html",
    "title": "50projects50days/index.html at main · tianheg/50projects50days",
    "count": 1,
    "uniques": 1
  },
  {
    "path": "/tianheg/50projects50days/blob/main/progress-steps/README.md",
    "title": "50projects50days/README.md at main · tianheg/50projects50days",
    "count": 1,
    "uniques": 1
  },
  {
    "path": "/tianheg/50projects50days/blob/main/README.md",
    "title": "50projects50days/README.md at main · tianheg/50projects50days",
    "count": 1,
    "uniques": 1
  },
  {
    "path": "/tianheg/50projects50days/blob/main/rotating-nav-animation/README.md",
    "title": "50projects50days/README.md at main · tianheg/50projects50days",
    "count": 1,
    "uniques": 1
  }
]